pandoc_include/__init__.py
pandoc_include/config.py
pandoc_include/format_heuristics.py
pandoc_include/main.py
pandoc_include-1.4.3.dist-info/LICENSE
pandoc_include-1.4.3.dist-info/METADATA
pandoc_include-1.4.3.dist-info/WHEEL
pandoc_include-1.4.3.dist-info/entry_points.txt
pandoc_include-1.4.3.dist-info/top_level.txt
pandoc_include-1.4.3.dist-info/RECORD
