Metadata-Version: 2.2
Name: pandoc-include
Version: 1.4.3
Summary: Pandoc filter to allow file and header includes
Author-email: DCsunset <DCsunset@protonmail.com>
License: MIT
Project-URL: homepage, https://github.com/DCsunset/pandoc-include
Keywords: pandoc,pandocfilters,markdown,latex
Classifier: Environment :: Console
Classifier: Intended Audience :: End Users/Desktop
Classifier: Programming Language :: Python
Classifier: License :: OSI Approved :: MIT License
Requires-Python: >=3.7
License-File: LICENSE
Requires-Dist: panflute>=2.0.5
Requires-Dist: natsort>=7
Requires-Dist: lxml>=4.9.2
Provides-Extra: pypi
Requires-Dist: build; extra == "pypi"
Requires-Dist: twine; extra == "pypi"
Requires-Dist: wheel; extra == "pypi"
